xcrun/__init__.py
xcrun/simctl/__init__.py
xcrun/simctl/device.py
xcrun/simctl/device_pair.py
xcrun/simctl/device_type.py
xcrun/simctl/listall.py
xcrun/simctl/runtime.py
xcrun/simctl/simctl.py
xcrun-0.1.dist-info/DESCRIPTION.rst
xcrun-0.1.dist-info/METADATA
xcrun-0.1.dist-info/RECORD
xcrun-0.1.dist-info/WHEEL
xcrun-0.1.dist-info/metadata.json
xcrun-0.1.dist-info/top_level.txt
